zscaler/__init__.py
zscaler/api_client.py
zscaler/cache/__init__.py
zscaler/cache/cache.py
zscaler/cache/no_op_cache.py
zscaler/cache/zscaler_cache.py
zscaler/config/__init__.py
zscaler/config/config_setter.py
zscaler/config/config_validator.py
zscaler/constants.py
zscaler/error_messages.py
zscaler/errors/__init__.py
zscaler/errors/error.py
zscaler/errors/graphql_error.py
zscaler/errors/http_error.py
zscaler/errors/response_checker.py
zscaler/errors/zscaler_api_error.py
zscaler/exceptions/__init__.py
zscaler/exceptions/exceptions.py
zscaler/helpers.py
zscaler/logger.py
zscaler/oneapi_client.py
zscaler/oneapi_collection.py
zscaler/oneapi_http_client.py
zscaler/oneapi_oauth_client.py
zscaler/oneapi_object.py
zscaler/oneapi_response.py
zscaler/ratelimiter/__init__.py
zscaler/ratelimiter/ratelimiter.py
zscaler/request_executor.py
zscaler/types.py
zscaler/user_agent.py
zscaler/utils.py
zscaler/zcc/__init__.py
zscaler/zcc/admin_user.py
zscaler/zcc/company.py
zscaler/zcc/devices.py
zscaler/zcc/entitlements.py
zscaler/zcc/fail_open_policy.py
zscaler/zcc/forwarding_profile.py
zscaler/zcc/legacy.py
zscaler/zcc/models/admin_roles.py
zscaler/zcc/models/admin_user.py
zscaler/zcc/models/devices.py
zscaler/zcc/models/failopenpolicy.py
zscaler/zcc/models/forwardingprofile.py
zscaler/zcc/models/getcompanyinfo.py
zscaler/zcc/models/manage_pass.py
zscaler/zcc/models/secrets_otp.py
zscaler/zcc/models/secrets_passwords.py
zscaler/zcc/models/trustednetworks.py
zscaler/zcc/models/webappservice.py
zscaler/zcc/models/webpolicy.py
zscaler/zcc/models/webprivacy.py
zscaler/zcc/models/zdxgroupentitlements.py
zscaler/zcc/models/zpagroupentitlements.py
zscaler/zcc/secrets.py
zscaler/zcc/trusted_networks.py
zscaler/zcc/web_app_service.py
zscaler/zcc/web_policy.py
zscaler/zcc/web_privacy.py
zscaler/zcc/zcc_service.py
zscaler/zdx/__init__.py
zscaler/zdx/admin.py
zscaler/zdx/alerts.py
zscaler/zdx/apps.py
zscaler/zdx/devices.py
zscaler/zdx/inventory.py
zscaler/zdx/legacy.py
zscaler_sdk_python-1.9.11.dist-info/LICENSE.md
zscaler_sdk_python-1.9.11.dist-info/METADATA
zscaler_sdk_python-1.9.11.dist-info/WHEEL
zscaler_sdk_python-1.9.11.dist-info/RECORD
