Metadata-Version: 2.1
Name: zscaler-sdk-python
Version: 1.9.11
Summary: Official Python SDK for the Zscaler Products
Home-page: https://github.com/zscaler/zscaler-sdk-python
License: MIT
Keywords: zscaler,sdk,zpa,zia,zdx,zcc,ztw,zwa,zidentity
Author: Zscaler, Inc.
Author-email: devrel@zscaler.com
Requires-Python: >=3.9.2,<4.0
Classifier: Development Status :: 5 - Production/Stable
Classifier: Intended Audience :: Developers
Classifier: License :: OSI Approved :: MIT License
Classifier: Operating System :: OS Independent
Classifier: Programming Language :: Python :: 3
Classifier: Programming Language :: Python :: 3.10
Classifier: Programming Language :: Python :: 3.11
Classifier: Programming Language :: Python :: 3.12
Classifier: Programming Language :: Python :: 3.9
Classifier: Topic :: Security
Classifier: Topic :: Software Development :: Libraries :: Python Modules
Provides-Extra: dev
Requires-Dist: PyJWT (>=2.10.1)
Requires-Dist: aenum (>=3.1.11)
Requires-Dist: arrow (>=1.3.0)
Requires-Dist: cryptography (>=45.0.2)
Requires-Dist: flatdict (>=4.0.0)
Requires-Dist: jwcrypto (>=1.5.6)
Requires-Dist: pydash (>=8.0.3)
Requires-Dist: python-box (>=7.3.0)
Requires-Dist: python-dateutil (>=2.9.0)
Requires-Dist: pytz (>=2024.2)
Requires-Dist: pyyaml (>=6.0.0)
Requires-Dist: requests (>=2.32.3)
Requires-Dist: urllib3 (>=2.6.0)
Project-URL: Bug Tracker, https://github.com/zscaler/zscaler-sdk-python/issues
Project-URL: Documentation, https://zscaler-sdk-python.readthedocs.io
Project-URL: Repository, https://github.com/zscaler/zscaler-sdk-python
